monistode_binutils_shared/__init__.py
monistode_binutils_shared/bytearray.py
monistode_binutils_shared/executable.py
monistode_binutils_shared/location.py
monistode_binutils_shared/object_manager.py
monistode_binutils_shared/py.typed
monistode_binutils_shared/relocation.py
monistode_binutils_shared/section/__init__.py
monistode_binutils_shared/section/common.py
monistode_binutils_shared/section/data.py
monistode_binutils_shared/section/relocation_table.py
monistode_binutils_shared/section/section_type.py
monistode_binutils_shared/section/symbol_table.py
monistode_binutils_shared/section/text.py
monistode_binutils_shared/segment/__init__.py
monistode_binutils_shared/segment/common.py
monistode_binutils_shared/segment/data.py
monistode_binutils_shared/segment/relocations.py
monistode_binutils_shared/segment/symbols.py
monistode_binutils_shared/segment/text.py
monistode_binutils_shared/symbol.py
monistode_binutils_shared-0.1.18.dist-info/METADATA
monistode_binutils_shared-0.1.18.dist-info/WHEEL
monistode_binutils_shared-0.1.18.dist-info/RECORD
